tasker/__init__.py
tasker/main.py
tasker/project_cmd.py
tasker/project_tasks.py
tasker/vpn_cmd.py
tasker/vpn_tasks.py
tasker/waf_cmd.py
tasker/waf_tasks.py
tasker/utils/__init__.py
tasker/utils/email.py
tasker/utils/git.py
tasker/utils/project.py
tasker/utils/registry.py
tasker/utils/tailscale_api.py
tasker/utils/user.py
tasker/utils/validate.py
steinwurf_tasker-3.0.2.dist-info/METADATA
steinwurf_tasker-3.0.2.dist-info/WHEEL
steinwurf_tasker-3.0.2.dist-info/entry_points.txt
steinwurf_tasker-3.0.2.dist-info/top_level.txt
steinwurf_tasker-3.0.2.dist-info/RECORD
