Metadata-Version: 2.4
Name: steinwurf-tasker
Version: 3.0.2
Summary: A tool for handling automated tasks in Steinwurf.
Requires-Dist: invoke
Requires-Dist: fabric
Requires-Dist: invocations
Requires-Dist: giturlparse
Requires-Dist: semver
Requires-Dist: steinnews
Requires-Dist: PyGithub
Requires-Dist: decorator
Dynamic: description
Dynamic: description-content-type
Dynamic: requires-dist
Dynamic: summary
